<?xml version="1.0"?>
<!DOCTYPE hibernate-mapping PUBLIC "-//Hibernate/Hibernate Mapping DTD 3.0//EN"
"http://hibernate.sourceforge.net/hibernate-mapping-3.0.dtd">
<!-- Generated 2015-5-8 19:54:47 by Hibernate Tools 3.4.0.CR1 -->
<hibernate-mapping package="cn.edu.nju.oa.domain">
	<class name="Role" table="ROLE">
		<id name="id" type="java.lang.Long">
			<column name="ID" />
			<generator class="native" />
		</id>
		<property name="name" type="java.lang.String">
			<column name="NAME" />
		</property>
		<property name="description" type="java.lang.String">
			<column name="DESCRIPTION" />
		</property>
		<set name="users" table="ROLE_USER" inverse="false" lazy="false">
			<key>
				<column name="roleId" />
			</key>
			<many-to-many class="User" column="userId" />
		</set>

		<!-- privileges属性，本类与Privilege是多对多关系 -->
		<set name="privileges" table="ROLE_PRIVILEGE" lazy="false">
			<key column="roleId"></key>
			<many-to-many class="Privilege" column="privilegeId"></many-to-many>
		</set>
	</class>
</hibernate-mapping>
